{"version":"3","listProblem":[{
  "tool": "Code Inspection",
  "category": "General",
  "type": "Kotlin annotator",
  "tags": [
    "Sanity"
  ],
  "severity": "Critical",
  "comment": "'val Project.libs: LibrariesForLibs' can't be called in this context by implicit receiver. Use the explicit one if necessary",
  "detailsInfo": "Allows viewing the problems reported by the Kotlin annotator: compilation problems, references unresolved by the IDE, and so on.",
  "sources": [
    {
      "type": "file",
      "path": "build.gradle.kts",
      "language": "kotlin",
      "line": 2,
      "offset": 11,
      "length": 4,
      "code": {
        "startLine": 1,
        "length": 4,
        "offset": 20,
        "surroundingCode": "plugins {\n    alias(libs.plugins.javiersc.hubdle)\n}\n"
      }
    }
  ],
  "attributes": {
    "module": "detekt-rules",
    "inspectionName": "KotlinAnnotator"
  },
  "hash": "b222bf11fce63fe220d1973d2459fd26d013f13c9e19765a30b9e7c316f1063f"
},{
  "tool": "Code Inspection",
  "category": "General",
  "type": "Kotlin annotator",
  "tags": [
    "Sanity"
  ],
  "severity": "Critical",
  "comment": "Cannot access class 'org.gradle.accessors.dm.LibrariesForLibs'. Check your module classpath for missing or conflicting dependencies",
  "detailsInfo": "Allows viewing the problems reported by the Kotlin annotator: compilation problems, references unresolved by the IDE, and so on.",
  "sources": [
    {
      "type": "file",
      "path": "build.gradle.kts",
      "language": "kotlin",
      "line": 2,
      "offset": 11,
      "length": 4,
      "code": {
        "startLine": 1,
        "length": 4,
        "offset": 20,
        "surroundingCode": "plugins {\n    alias(libs.plugins.javiersc.hubdle)\n}\n"
      }
    }
  ],
  "attributes": {
    "module": "detekt-rules",
    "inspectionName": "KotlinAnnotator"
  },
  "hash": "9054a1cef87c6af3d6210c43c956359685357404f1e9835957dd40d200805533"
},{
  "tool": "Code Inspection",
  "category": "General",
  "type": "Kotlin annotator",
  "tags": [
    "Sanity"
  ],
  "severity": "Critical",
  "comment": "Function invocation 'plugins(...)' expected",
  "detailsInfo": "Allows viewing the problems reported by the Kotlin annotator: compilation problems, references unresolved by the IDE, and so on.",
  "sources": [
    {
      "type": "file",
      "path": "build.gradle.kts",
      "language": "kotlin",
      "line": 2,
      "offset": 16,
      "length": 7,
      "code": {
        "startLine": 1,
        "length": 7,
        "offset": 25,
        "surroundingCode": "plugins {\n    alias(libs.plugins.javiersc.hubdle)\n}\n"
      }
    }
  ],
  "attributes": {
    "module": "detekt-rules",
    "inspectionName": "KotlinAnnotator"
  },
  "hash": "eec37a653bfd6188572ba2e2192c8657d04e4624073b73ebef98b09c4b1c0176"
},{
  "tool": "Code Inspection",
  "category": "General",
  "type": "Kotlin annotator",
  "tags": [
    "Sanity"
  ],
  "severity": "Critical",
  "comment": "Unresolved reference. None of the following candidates is applicable because of receiver type mismatch: public fun Project.plugins(block: PluginDependenciesSpec.() -> Unit): Nothing defined in org.gradle.kotlin.dsl",
  "detailsInfo": "Allows viewing the problems reported by the Kotlin annotator: compilation problems, references unresolved by the IDE, and so on.",
  "sources": [
    {
      "type": "file",
      "path": "build.gradle.kts",
      "language": "kotlin",
      "line": 2,
      "offset": 16,
      "length": 7,
      "code": {
        "startLine": 1,
        "length": 7,
        "offset": 25,
        "surroundingCode": "plugins {\n    alias(libs.plugins.javiersc.hubdle)\n}\n"
      }
    }
  ],
  "attributes": {
    "module": "detekt-rules",
    "inspectionName": "KotlinAnnotator"
  },
  "hash": "a4be68644b2370561ac10956d9989f8a1d6f0bf7da75b8146435dfc504130ce3"
},{
  "tool": "Code Inspection",
  "category": "General",
  "type": "Kotlin annotator",
  "tags": [
    "Sanity"
  ],
  "severity": "Critical",
  "comment": "'val Project.libs: LibrariesForLibs' can't be called in this context by implicit receiver. Use the explicit one if necessary",
  "detailsInfo": "Allows viewing the problems reported by the Kotlin annotator: compilation problems, references unresolved by the IDE, and so on.",
  "sources": [
    {
      "type": "file",
      "path": "banned-import/build.gradle.kts",
      "language": "kotlin",
      "line": 2,
      "offset": 11,
      "length": 4,
      "code": {
        "startLine": 1,
        "length": 4,
        "offset": 20,
        "surroundingCode": "plugins {\n    alias(libs.plugins.javiersc.hubdle)\n}\n"
      }
    }
  ],
  "attributes": {
    "module": "detekt-rules.banned-import",
    "inspectionName": "KotlinAnnotator"
  },
  "hash": "eddc596a596d4548deb12d4010c037ee6a3129e036aada34924f1de4b6f7ec3e"
},{
  "tool": "Code Inspection",
  "category": "General",
  "type": "Kotlin annotator",
  "tags": [
    "Sanity"
  ],
  "severity": "Critical",
  "comment": "Cannot access class 'org.gradle.accessors.dm.LibrariesForLibs'. Check your module classpath for missing or conflicting dependencies",
  "detailsInfo": "Allows viewing the problems reported by the Kotlin annotator: compilation problems, references unresolved by the IDE, and so on.",
  "sources": [
    {
      "type": "file",
      "path": "banned-import/build.gradle.kts",
      "language": "kotlin",
      "line": 2,
      "offset": 11,
      "length": 4,
      "code": {
        "startLine": 1,
        "length": 4,
        "offset": 20,
        "surroundingCode": "plugins {\n    alias(libs.plugins.javiersc.hubdle)\n}\n"
      }
    }
  ],
  "attributes": {
    "module": "detekt-rules.banned-import",
    "inspectionName": "KotlinAnnotator"
  },
  "hash": "75a42f16fafc3420e95eb9901736e3e3f70665431eae333e137de32d5a9bcd7d"
},{
  "tool": "Code Inspection",
  "category": "General",
  "type": "Kotlin annotator",
  "tags": [
    "Sanity"
  ],
  "severity": "Critical",
  "comment": "Function invocation 'plugins(...)' expected",
  "detailsInfo": "Allows viewing the problems reported by the Kotlin annotator: compilation problems, references unresolved by the IDE, and so on.",
  "sources": [
    {
      "type": "file",
      "path": "banned-import/build.gradle.kts",
      "language": "kotlin",
      "line": 2,
      "offset": 16,
      "length": 7,
      "code": {
        "startLine": 1,
        "length": 7,
        "offset": 25,
        "surroundingCode": "plugins {\n    alias(libs.plugins.javiersc.hubdle)\n}\n"
      }
    }
  ],
  "attributes": {
    "module": "detekt-rules.banned-import",
    "inspectionName": "KotlinAnnotator"
  },
  "hash": "389f1e71cdb28e89a67ed131a41dc43ce2b6dcd54812264f7afd545eeb1a9d79"
},{
  "tool": "Code Inspection",
  "category": "General",
  "type": "Kotlin annotator",
  "tags": [
    "Sanity"
  ],
  "severity": "Critical",
  "comment": "Unresolved reference. None of the following candidates is applicable because of receiver type mismatch: public fun Project.plugins(block: PluginDependenciesSpec.() -> Unit): Nothing defined in org.gradle.kotlin.dsl",
  "detailsInfo": "Allows viewing the problems reported by the Kotlin annotator: compilation problems, references unresolved by the IDE, and so on.",
  "sources": [
    {
      "type": "file",
      "path": "banned-import/build.gradle.kts",
      "language": "kotlin",
      "line": 2,
      "offset": 16,
      "length": 7,
      "code": {
        "startLine": 1,
        "length": 7,
        "offset": 25,
        "surroundingCode": "plugins {\n    alias(libs.plugins.javiersc.hubdle)\n}\n"
      }
    }
  ],
  "attributes": {
    "module": "detekt-rules.banned-import",
    "inspectionName": "KotlinAnnotator"
  },
  "hash": "9f5be1358acfc55b3fc1f25489f6f074a6346c8fb57cc2eb91c6de347f25bc60"
}]}